graphroam/__init__.py
graphroam/graphroam.py
GraphRoam-0.1.0.dist-info/LICENCE
GraphRoam-0.1.0.dist-info/METADATA
GraphRoam-0.1.0.dist-info/WHEEL
GraphRoam-0.1.0.dist-info/top_level.txt
GraphRoam-0.1.0.dist-info/RECORD
